deepdelineator/__init__.py
deepdelineator/dataset.py
deepdelineator/model.py
deepdelineator/utils.py
deepdelineator/weights/TCN.pt
deepdelineator/weights/U_GRU.pt
deepdelineator/weights/U_NET.pt
deepdelineator/weights/U_TCN.pt
deepdelineator-0.1.1.dist-info/LICENSE
deepdelineator-0.1.1.dist-info/METADATA
deepdelineator-0.1.1.dist-info/WHEEL
deepdelineator-0.1.1.dist-info/RECORD
