Metadata-Version: 2.1
Name: deepdelineator
Version: 0.1.1
Summary: 
Author: Nicolas Aguirre
Author-email: nicolasaguirre90@hotmail.com
Requires-Python: >=3.12,<4.0
Classifier: Programming Language :: Python :: 3
Classifier: Programming Language :: Python :: 3.12
Requires-Dist: ipykernel (>=6.29.5,<7.0.0)
Requires-Dist: matplotlib (>=3.10.0,<4.0.0)
Requires-Dist: numpy (>=2.2.1,<3.0.0)
Requires-Dist: pandas (>=2.2.3,<3.0.0)
Requires-Dist: scikit-learn (>=1.6.1,<2.0.0)
Requires-Dist: scipy (>=1.15.1,<2.0.0)
Requires-Dist: torch (>=2.5.1,<3.0.0)
Requires-Dist: tqdm (>=4.67.1,<5.0.0)
